dns_validator/__init__.py
dns_validator/__main__.py
dns_validator/api_key_manager.py
dns_validator/dns_validator.py
dns_validator-2.6.0.dist-info/licenses/LICENSE
dns_validator-2.6.0.dist-info/METADATA
dns_validator-2.6.0.dist-info/WHEEL
dns_validator-2.6.0.dist-info/entry_points.txt
dns_validator-2.6.0.dist-info/top_level.txt
dns_validator-2.6.0.dist-info/RECORD
