Metadata-Version: 2.4
Name: dns-validator
Version: 2.6.0
Summary: A comprehensive DNS validation tool with delegation, propagation, and provider settings checks
Home-page: https://github.com/HereLiesHugo/dns-validator
Author: Matisse Urquhart
Author-email: me@maturqu.com
Project-URL: Bug Reports, https://github.com/HereLiesHugo/dns-validator/issues
Project-URL: Source, https://github.com/HereLiesHugo/dns-validator
Project-URL: Documentation, https://github.com/HereLiesHugo/dns-validator#readme
Keywords: dns validation delegation propagation cloudflare nameservers cli
Classifier: Development Status :: 4 - Beta
Classifier: Intended Audience :: System Administrators
Classifier: Intended Audience :: Developers
Classifier: Topic :: Internet :: Name Service (DNS)
Classifier: Topic :: System :: Networking
Classifier: License :: OSI Approved :: GNU Affero General Public License v3
Classifier: Programming Language :: Python :: 3
Classifier: Programming Language :: Python :: 3.7
Classifier: Programming Language :: Python :: 3.8
Classifier: Programming Language :: Python :: 3.9
Classifier: Programming Language :: Python :: 3.10
Classifier: Programming Language :: Python :: 3.11
Classifier: Operating System :: OS Independent
Classifier: Environment :: Console
Requires-Python: >=3.7
License-File: LICENSE
Requires-Dist: click>=8.0.0
Requires-Dist: dnspython>=2.3.0
Requires-Dist: requests>=2.28.0
Requires-Dist: colorama>=0.4.6
Requires-Dist: tabulate>=0.9.0
Requires-Dist: pycryptodome>=3.15.0
Requires-Dist: cryptography>=41.0.0
Requires-Dist: setuptools>=65.5.0
Requires-Dist: boto3>=1.26.0
Requires-Dist: google-cloud-dns>=0.34.0
Requires-Dist: azure-mgmt-dns>=8.0.0
Requires-Dist: azure-identity>=1.12.0
Requires-Dist: azure-core>=1.24.0
Requires-Dist: concurrent.futures>=3.1.1; python_version < "3.2"
Requires-Dist: pathlib>=1.0.1; python_version < "3.4"
Requires-Dist: ipaddress>=1.0.23; python_version < "3.3"
Requires-Dist: pyOpenSSL>=23.0.0
Requires-Dist: certifi>=2022.12.7
Requires-Dist: urllib3>=1.26.0
Requires-Dist: pyperclip>=1.8.0
Dynamic: author
Dynamic: author-email
Dynamic: classifier
Dynamic: description
Dynamic: description-content-type
Dynamic: home-page
Dynamic: keywords
Dynamic: license-file
Dynamic: project-url
Dynamic: requires-dist
Dynamic: requires-python
Dynamic: summary
